z3c.authenticator-2.0-py3.9-nspkg.pth
z3c/authenticator/README.txt
z3c/authenticator/__init__.py
z3c/authenticator/authentication.py
z3c/authenticator/configure.zcml
z3c/authenticator/credential.py
z3c/authenticator/credential.zcml
z3c/authenticator/event.py
z3c/authenticator/group.py
z3c/authenticator/group.txt
z3c/authenticator/group.zcml
z3c/authenticator/interfaces.py
z3c/authenticator/principal.py
z3c/authenticator/principal.zcml
z3c/authenticator/principalregistry.py
z3c/authenticator/principalregistry.zcml
z3c/authenticator/testing.py
z3c/authenticator/tests.py
z3c/authenticator/user.py
z3c/authenticator/user.zcml
z3c/authenticator/vocabulary.py
z3c/authenticator/vocabulary.txt
z3c/authenticator/widget.pt
z3c/authenticator/widget.py
z3c/authenticator/widget.zcml
z3c/authenticator/widget_search_form.pt
z3c/authenticator/widget_source_search_input.pt
z3c/authenticator/browser/__init__.py
z3c/authenticator/browser/authenticator.py
z3c/authenticator/browser/authenticator.zcml
z3c/authenticator/browser/configure.zcml
z3c/authenticator/browser/credential.py
z3c/authenticator/browser/credential.zcml
z3c/authenticator/browser/group.py
z3c/authenticator/browser/group.zcml
z3c/authenticator/browser/login.pt
z3c/authenticator/browser/login.py
z3c/authenticator/browser/login.zcml
z3c/authenticator/browser/user.py
z3c/authenticator/browser/user.zcml
z3c.authenticator-2.0.dist-info/LICENSE.txt
z3c.authenticator-2.0.dist-info/METADATA
z3c.authenticator-2.0.dist-info/WHEEL
z3c.authenticator-2.0.dist-info/namespace_packages.txt
z3c.authenticator-2.0.dist-info/top_level.txt
z3c.authenticator-2.0.dist-info/RECORD
