Metadata-Version: 2.1
Name: z3c.authenticator
Version: 2.0
Summary: IAuthentication implementation for for Zope3
Home-page: https://github.com/zopefoundation/z3c.authenticator
Author: Roger Ineichen and the Zope Community
Author-email: zope-dev@zope.dev
License: ZPL 2.1
Keywords: zope3 z3c authentication auth group
Classifier: Development Status :: 5 - Production/Stable
Classifier: Environment :: Web Environment
Classifier: Intended Audience :: Developers
Classifier: License :: OSI Approved :: Zope Public License
Classifier: Programming Language :: Python
Classifier: Programming Language :: Python :: 3
Classifier: Programming Language :: Python :: 3.7
Classifier: Programming Language :: Python :: 3.8
Classifier: Programming Language :: Python :: 3.9
Classifier: Programming Language :: Python :: 3.10
Classifier: Programming Language :: Python :: 3.11
Classifier: Programming Language :: Python :: Implementation :: CPython
Classifier: Programming Language :: Python :: Implementation :: PyPy
Classifier: Natural Language :: English
Classifier: Operating System :: OS Independent
Classifier: Topic :: Internet :: WWW/HTTP
Classifier: Framework :: Zope :: 3
Requires-Python: >=3.7
License-File: LICENSE.txt
Requires-Dist: setuptools
Requires-Dist: z3c.contents
Requires-Dist: z3c.form
Requires-Dist: z3c.formui
Requires-Dist: z3c.template
Requires-Dist: zope.authentication
Requires-Dist: zope.component
Requires-Dist: zope.container
Requires-Dist: zope.deprecation
Requires-Dist: zope.dublincore
Requires-Dist: zope.event
Requires-Dist: zope.i18n
Requires-Dist: zope.interface
Requires-Dist: zope.lifecycleevent
Requires-Dist: zope.location
Requires-Dist: zope.password
Requires-Dist: zope.principalregistry
Requires-Dist: zope.publisher
Requires-Dist: zope.schema
Requires-Dist: zope.security
Requires-Dist: zope.session
Requires-Dist: zope.site
Requires-Dist: zope.traversing
Provides-Extra: configurator
Requires-Dist: z3c.configurator ; extra == 'configurator'
Provides-Extra: test
Requires-Dist: z3c.testing (>=1.0.0a3) ; extra == 'test'
Requires-Dist: zope.testing ; extra == 'test'
